README.md
setup.cfg
setup.py
src/geo_calculator.py
src/geo_calculator.egg-info/PKG-INFO
src/geo_calculator.egg-info/SOURCES.txt
src/geo_calculator.egg-info/dependency_links.txt
src/geo_calculator.egg-info/top_level.txt