Metadata-Version: 1.1
Name: geo-calculator
Version: 0.1.2
Summary: Multi function Geo Location calculator
Home-page: http://joaofilipesabinoesperancinha.nl/main
Author: João Esperancinha
Author-email: jofisaes@gmail.com
License: UNKNOWN
Download-URL: https://github.com/user/reponame/archive/v_01.tar.gz
Keywords: geo,location,latitude,longitude
Platform: UNKNOWN
Classifier: Development Status :: 3 - Alpha
Classifier: Intended Audience :: Developers
Classifier: Topic :: Software Development :: Build Tools
Classifier: License :: OSI Approved :: Apache Software License
Classifier: Programming Language :: Python :: 3
Classifier: Programming Language :: Python :: 3.4
Classifier: Programming Language :: Python :: 3.5
Classifier: Programming Language :: Python :: 3.6
